MANIFEST.in
PKG-INFO
README.txt
setup.cfg
setup.py
soniatheme/.DS_Store
soniatheme/__init__.py
soniatheme/configure.zcml
soniatheme.egg-info/PKG-INFO
soniatheme.egg-info/SOURCES.txt
soniatheme.egg-info/dependency_links.txt
soniatheme.egg-info/entry_points.txt
soniatheme.egg-info/namespace_packages.txt
soniatheme.egg-info/not-zip-safe
soniatheme.egg-info/requires.txt
soniatheme.egg-info/top_level.txt
soniatheme/theme/__init__.py
soniatheme/theme/configure.zcml
soniatheme/theme/profiles.zcml
soniatheme/theme/setuphandlers.py
soniatheme/theme/skins.zcml
soniatheme/theme/tests.py
soniatheme/theme/version.txt
soniatheme/theme/version.txt~
soniatheme/theme/browser/__init__.py
soniatheme/theme/browser/configure.zcml
soniatheme/theme/browser/interfaces.py
soniatheme/theme/browser/viewlet.pt
soniatheme/theme/browser/viewlets.py
soniatheme/theme/browser/images/README.txt
soniatheme/theme/browser/stylesheets/README.txt
soniatheme/theme/browser/stylesheets/main.css
soniatheme/theme/profiles/default/cssregistry.xml
soniatheme/theme/profiles/default/import_steps.xml
soniatheme/theme/profiles/default/jsregistry.xml
soniatheme/theme/profiles/default/skins.xml
soniatheme/theme/profiles/default/soniatheme.theme_various.txt
soniatheme/theme/profiles/default/viewlets.xml
soniatheme/theme/profiles/default/viewlets.xml~
soniatheme/theme/skins/soniatheme_theme_custom_images/CONTENT.txt
soniatheme/theme/skins/soniatheme_theme_custom_images/bg_bottom.png
soniatheme/theme/skins/soniatheme_theme_custom_images/bg_top.gif
soniatheme/theme/skins/soniatheme_theme_custom_images/clanak.gif
soniatheme/theme/skins/soniatheme_theme_custom_images/datum.gif
soniatheme/theme/skins/soniatheme_theme_custom_images/header.gif
soniatheme/theme/skins/soniatheme_theme_custom_images/lijevo.gif
soniatheme/theme/skins/soniatheme_theme_custom_images/plavo.gif
soniatheme/theme/skins/soniatheme_theme_custom_images/strelica.gif
soniatheme/theme/skins/soniatheme_theme_custom_images/strelica2.gif
soniatheme/theme/skins/soniatheme_theme_custom_templates/CONTENT.txt
soniatheme/theme/skins/soniatheme_theme_styles/CONTENT.txt
soniatheme/theme/skins/soniatheme_theme_styles/base.css.dtml
soniatheme/theme/skins/soniatheme_theme_styles/base_properties.props
