Metadata-Version: 1.0
Name: soniatheme
Version: 0.2dev
Summary: An installable theme for Plone 3.0
Home-page: http://svn.plone.org/svn/collective/
Author: Plone Collective
Author-email: product-developers@lists.plone.org
License: GPL
Keywords: web zope plone theme
Platform: UNKNOWN
Classifier: Framework :: Plone
Classifier: Framework :: Zope2
Classifier: Framework :: Zope3
Classifier: Programming Language :: Python
Classifier: Topic :: Software Development :: Libraries :: Python Modules
